matgraphdb/__init__.py
matgraphdb/_version.py
matgraphdb/calculations/README.md
matgraphdb/calculations/__init__.py
matgraphdb/calculations/calc_manager.py
matgraphdb/calculations/job_scheduler_generator.py
matgraphdb/calculations/parsers.py
matgraphdb/calculations/slurm_job_launcher.py
matgraphdb/calculations/dft_calcs/__init__.py
matgraphdb/calculations/dft_calcs/calc_generators.py
matgraphdb/calculations/dft_calcs/chargemol_calc_setup.py
matgraphdb/calculations/dft_calcs/generate_calc_dir.py
matgraphdb/calculations/dft_calcs/generate_chargemol.py
matgraphdb/calculations/dft_calcs/remove_wavecar.py
matgraphdb/calculations/mat_calcs/__init__.py
matgraphdb/calculations/mat_calcs/bond_stats_calc.py
matgraphdb/calculations/mat_calcs/bonding_calc.py
matgraphdb/calculations/mat_calcs/chemenv_calc.py
matgraphdb/calculations/mat_calcs/embeddings.py
matgraphdb/calculations/mat_calcs/similarity_calc.py
matgraphdb/calculations/mat_calcs/wyckoff_calc.py
matgraphdb/core/__init__.py
matgraphdb/core/edges.py
matgraphdb/core/generator_store.py
matgraphdb/core/graph_db.py
matgraphdb/core/nodes.py
matgraphdb/core/utils.py
matgraphdb/graph_kit/__init__.py
matgraphdb/graph_kit/data.py
matgraphdb/graph_kit/graph_manager.py
matgraphdb/graph_kit/metadata.py
matgraphdb/graph_kit/nodes.py
matgraphdb/graph_kit/relationships.py
matgraphdb/graph_kit/utils.py
matgraphdb/graph_kit/graph_tool/__init__.py
matgraphdb/graph_kit/graph_tool/graph_tool_analyzer.py
matgraphdb/graph_kit/neo4j/README.md
matgraphdb/graph_kit/neo4j/__init__.py
matgraphdb/graph_kit/neo4j/neo4j_analysis.py
matgraphdb/graph_kit/neo4j/neo4j_experiment_manager.py
matgraphdb/graph_kit/neo4j/neo4j_gds_manager.py
matgraphdb/graph_kit/neo4j/neo4j_manager.py
matgraphdb/graph_kit/neo4j/utils.py
matgraphdb/graph_kit/pyg/__init__.py
matgraphdb/graph_kit/pyg/algo.py
matgraphdb/graph_kit/pyg/callbacks.py
matgraphdb/graph_kit/pyg/encoders.py
matgraphdb/graph_kit/pyg/graph_models.py
matgraphdb/graph_kit/pyg/graph_trainer.py
matgraphdb-0.2.0.dist-info/LICENSE
matgraphdb-0.2.0.dist-info/METADATA
matgraphdb-0.2.0.dist-info/WHEEL
matgraphdb-0.2.0.dist-info/top_level.txt
matgraphdb-0.2.0.dist-info/RECORD
