Metadata-Version: 2.2
Name: matgraphdb
Version: 0.2.0
Summary: Welcome to MatGraphDB, a powerful Python package designed to interface with primary and graph databases for advanced material analysis.
Author-email: Logan Lang <lllang@mix.wvu.edu>
License: MIT License
Project-URL: Repository, https://github.com/romerogroup/MatGraphDB
Project-URL: Issues, https://github.com/romerogroup/MatGraphDB/issues
Project-URL: Changelog, https://github.com/romerogroup/MatGraphDB/CHANGELOG.md
Keywords: materials,science,graph,database,python
Classifier: Programming Language :: Python :: 3
Requires-Python: >=3.8
License-File: LICENSE
Requires-Dist: pytest
Requires-Dist: setuptools
Requires-Dist: setuptools_scm
Requires-Dist: python-dotenv
Requires-Dist: numpy
Requires-Dist: pandas
Requires-Dist: scipy
Requires-Dist: matplotlib
Requires-Dist: seaborn
Requires-Dist: pyyaml
Requires-Dist: jupyterlab
Requires-Dist: nglview
Requires-Dist: ipywidgets
Requires-Dist: pylint
Requires-Dist: autopep8
Requires-Dist: pymatgen
Requires-Dist: parquetdb
Requires-Dist: variconfig
Provides-Extra: torch
Requires-Dist: torch; extra == "torch"
Requires-Dist: torchvision; extra == "torch"
Requires-Dist: torchaudio; extra == "torch"
Requires-Dist: pyg_lib; platform_system == "Linux" and extra == "torch"
Requires-Dist: torch_geometric; extra == "torch"
Requires-Dist: torch_scatter; extra == "torch"
Requires-Dist: torch_sparse; extra == "torch"
Requires-Dist: torch_cluster; extra == "torch"
Requires-Dist: torch_spline_conv; extra == "torch"
Provides-Extra: graph-tool
Requires-Dist: graph-tool; platform_system == "Linux" and extra == "graph-tool"
Provides-Extra: llm
Requires-Dist: openai; extra == "llm"
Requires-Dist: tiktoken; extra == "llm"
Provides-Extra: neo4j
Requires-Dist: neo4j; extra == "neo4j"
Provides-Extra: materials
Requires-Dist: ase; extra == "materials"
Requires-Dist: mendeleev; extra == "materials"
Requires-Dist: matminer; extra == "materials"
Requires-Dist: coxeter; extra == "materials"
Requires-Dist: crystals; extra == "materials"
Provides-Extra: dev
Requires-Dist: sphinx; extra == "dev"
Requires-Dist: sphinx_rtd_theme; extra == "dev"
